JiaoNiChengweiQuanzhanGongchengshiFullStackDeveloper/README.md
JiaoNiChengweiQuanzhanGongchengshiFullStackDeveloper/__init__.py
JiaoNiChengweiQuanzhanGongchengshiFullStackDeveloper/__main__.py
JiaoNiChengweiQuanzhanGongchengshiFullStackDeveloper/file.pdf
JiaoNiChengweiQuanzhanGongchengshiFullStackDeveloper/index.html
jiao_ni_chengwei_quanzhan_gongchengshi_full_stack_developer-2024.3.1.0.dist-info/METADATA
jiao_ni_chengwei_quanzhan_gongchengshi_full_stack_developer-2024.3.1.0.dist-info/WHEEL
jiao_ni_chengwei_quanzhan_gongchengshi_full_stack_developer-2024.3.1.0.dist-info/entry_points.txt
jiao_ni_chengwei_quanzhan_gongchengshi_full_stack_developer-2024.3.1.0.dist-info/top_level.txt
jiao_ni_chengwei_quanzhan_gongchengshi_full_stack_developer-2024.3.1.0.dist-info/RECORD
